opplast/__init__.py
opplast/constants.py
opplast/exceptions.py
opplast/logging.py
opplast/upload.py
opplast_v2-2.0.1.dist-info/LICENSE
opplast_v2-2.0.1.dist-info/METADATA
opplast_v2-2.0.1.dist-info/WHEEL
opplast_v2-2.0.1.dist-info/top_level.txt
opplast_v2-2.0.1.dist-info/RECORD
