Metadata-Version: 2.1
Name: opplast-v2
Version: 2.0.1
Summary: Upload videos to YouTube using geckodriver, Firefox profiles and Selenium.
Home-page: https://github.com/OwOHamper/opplast
Download-URL: https://github.com/OwOHamper/opplast/tarball/v2.0.1
Author: OwOHamper
Author-email: barca.teo@gmail.com
License: MIT
Classifier: Programming Language :: Python :: 3
Classifier: License :: OSI Approved :: MIT License
Classifier: Operating System :: OS Independent
Requires-Python: >=3.6
License-File: LICENSE
Requires-Dist: selenium <4
